gspumpndump/__init__.py
gspumpndump/logging.conf
gspumpndump/commands/__init__.py
gspumpndump/commands/gsdump.py
gspumpndump/commands/gspump.py
gspumpndump/config/__init__.py
gspumpndump/config/geoserver_config.py
gspumpndump/operations/__init__.py
gspumpndump/operations/dump_geoserver.py
gspumpndump/operations/pump_geoserver.py
gspumpndump/tests/__init__.py
gspumpndump/tests/dump_geoserver_tests.py
gspumpndump/tests/pump_geoserver_tests.py
gspumpndump-0.1.5.dist-info/DESCRIPTION.rst
gspumpndump-0.1.5.dist-info/METADATA
gspumpndump-0.1.5.dist-info/RECORD
gspumpndump-0.1.5.dist-info/WHEEL
gspumpndump-0.1.5.dist-info/entry_points.txt
gspumpndump-0.1.5.dist-info/metadata.json
gspumpndump-0.1.5.dist-info/top_level.txt
